yaml_requests/__init__.py
yaml_requests/__main__.py
yaml_requests/_main.py
yaml_requests/_plan.py
yaml_requests/_request.py
yaml_requests/_runner.py
yaml_requests/error.py
yaml_requests/logger/__init__.py
yaml_requests/logger/_console.py
yaml_requests/logger/_request.py
yaml_requests/utils/__init__.py
yaml_requests/utils/args.py
yaml_requests/utils/template.py
yaml_requests-0.16.2.dist-info/LICENSE
yaml_requests-0.16.2.dist-info/METADATA
yaml_requests-0.16.2.dist-info/WHEEL
yaml_requests-0.16.2.dist-info/entry_points.txt
yaml_requests-0.16.2.dist-info/top_level.txt
yaml_requests-0.16.2.dist-info/RECORD
