Metadata-Version: 2.1
Name: yaml_requests
Version: 0.16.2
Summary: A simple python app for sending a set of consecutive HTTP requests defined in YAML requests plan.
Author: Toni Kangas
License: MIT License
Project-URL: Homepage, https://github.com/kangasta/yaml_requests
Project-URL: Repository, https://github.com/kangasta/yaml_requests.git
Project-URL: Changelog, https://github.com/kangasta/yaml_requests/blob/main/CHANGELOG.md
Classifier: Programming Language :: Python :: 3
Classifier: License :: OSI Approved :: MIT License
Classifier: Operating System :: OS Independent
Requires-Python: >=3.9
License-File: LICENSE
Requires-Dist: ciou~=0.6
Requires-Dist: Jinja2~=3.0
Requires-Dist: pyyaml~=6.0
Requires-Dist: requests~=2.0
